{"DVDs":[{"Borrowed":"0","AudioDescription":"1","editor":{"Zipcode":"38000","Country":"unknown","Street":"proche du centre de la Terre","City":"Zion","Name":"last survivor editions","SIRET":"0000000000"},"PublishDate":"2021-01-30","Type":"0","Borrowable":"1","Length":"2:17:05","Title":"Matrix"},{"Borrowed":"0","AudioDescription":"0","editor":{"Zipcode":"38000","Country":"Pologne","Street":"dans un garage","City":"Wroclaw","Name":"CD projekts","SIRET":"9543186542"},"PublishDate":"2021-01-30","Type":"3","Borrowable":"1","Length":"1:12:14","Title":"Witcher"},{"Borrowed":"0","AudioDescription":"1","editor":{"Zipcode":"38000","Country":"extreme South","Street":"pôle Sud","City":"panguoria","Name":"le manchot pas droit","SIRET":"9831546785"},"PublishDate":"2021-01-30","Type":"4","Borrowable":"1","Length":"14:05","Title":"La marche des empereurs"},{"Borrowed":"0","AudioDescription":"1","editor":{"Zipcode":"38000","Country":"USA","Street":"9 rue du skate park","City":"Portland","Name":"skaterzz","SIRET":"9012864856"},"PublishDate":"2021-01-30","Type":"1","Borrowable":"1","Length":"11:11","Title":"Deftones - Live in Sydney"}],"CDs":[{"Borrowed":"0","editor":{"Zipcode":"38000","Country":"Allemagne","Street":"impasse élémentaire","City":"Dusseldorf","Name":"Adibou Ausgaben","SIRET":"6751398542"},"PublishDate":"2021-01-30","Type":"3","Borrowable":"1","NumberOfTracks":"10","Length":"36:45","Title":"Adibou à l'école"},{"Borrowed":"0","editor":{"Zipcode":"38000","Country":"USA","Street":"85 show pimp street","City":"Miami","Name":"Silicon Valley","SIRET":"9780230145"},"PublishDate":"2021-01-30","Type":"4","Borrowable":"1","NumberOfTracks":"12","Length":"48:04","Title":"Photoshop"},{"Borrowed":"0","editor":{"Zipcode":"38000","Country":"USA","Street":"somewhere on Punk avenue","City":"Los Angeles","Name":"destroy everything editions","SIRET":"0024556314"},"PublishDate":"2021-01-30","Type":"0","Borrowable":"1","NumberOfTracks":"15","Length":"58:02","Title":"The Offspring - Americana"},{"Borrowed":"0","editor":{"Zipcode":"38000","Country":"Heaven","Street":"ruelle de la sérénité","City":"Utopia","Name":"Deus edition","SIRET":"9999999999"},"PublishDate":"2021-01-30","Type":"2","Borrowable":"1","NumberOfTracks":"1","Length":"08:45:12","Title":"Forest ambiance"}],"Magazines":[{"Borrowed":"0","editor":{"Zipcode":"38000","Country":"France","Street":"rue du vroum","City":"Monaco","Name":"AutoMoto&Co","SIRET":"1547926875"},"PublishDate":"2021-01-30","Type":"5","Borrowable":"0","Title":"Auto moto","Frequency":"2","Author":"Les magazines qui roulent","NumberOfPages":"50"},{"Borrowed":"0","editor":{"Zipcode":"38000","Country":"France","Street":"avenue des sciences","City":"Paris","Name":"ScienceEditor","SIRET":"5987621468"},"PublishDate":"2021-01-30","Type":"1","Borrowable":"0","Title":"Science et vie","Frequency":"3","Author":"Les magazines de sciences","NumberOfPages":"75"},{"Borrowed":"0","editor":{"Zipcode":"38000","Country":"France","Street":"boulevard de la resistance","City":"Grenoble","Name":"edition Jean Moulin","SIRET":"8943201547"},"PublishDate":"2021-01-30","Type":"4","Borrowable":"0","Title":"Le Dauphiné libéré","Frequency":"0","Author":"Journal du dauphiné","NumberOfPages":"12"},{"Borrowed":"0","editor":{"Zipcode":"38000","Country":"France","Street":"ruelle du musée","City":"Orléans","Name":"edition vieille","SIRET":"9032105478"},"PublishDate":"2021-01-30","Type":"2","Borrowable":"0","Title":"un magazine d'histoire","Frequency":"4","Author":"Journal du musée","NumberOfPages":"36"}],"Books":[{"Borrowed":"0","editor":{"Zipcode":"38000","Country":"un pays","Street":"une rue","City":"une ville","Name":"un nom","SIRET":"un siret"},"PublishDate":"2021-01-30","Type":"1","Borrowable":"1","Title":"Design Pattern","Translated":"1","Author":"Eric Gamma","NumberOfPages":"300"},{"Borrowed":"0","editor":{"Zipcode":"38000","Country":"en Europe","Street":"quelque part","City":"dans une ville lointaine","Name":"chez un editeur","SIRET":"Siret"},"PublishDate":"2021-01-30","Type":"4","Borrowable":"1","Title":"L'art d'avoir toujours raison","Translated":"1","Author":"Arthur Schöpenhauer","NumberOfPages":"75"},{"Borrowed":"0","editor":{"Zipcode":"38000","Country":"sur un continent","Street":"paumé","City":"j'en sais rien","Name":"va savoir","SIRET":"qui sait?"},"PublishDate":"2021-01-30","Type":"0","Borrowable":"1","Title":"Le grands livre des robots","Translated":"1","Author":"Isaac Asimov","NumberOfPages":"2000"},{"Borrowed":"0","editor":{"Zipcode":"38000","Country":"USA","Street":"est ce important?","City":"pas d'inspiration","Name":"hippies&Co","SIRET":"nope"},"PublishDate":"2021-01-30","Type":"2","Borrowable":"1","Title":"Les portes de la perception","Translated":"1","Author":"Aldous Huxley","NumberOfPages":"215"}]}